slip/__init__.py
slip/slip.py
tio/__init__.py
tio/tio_protocol.py
tio/tio_session.py
tiotools/__init__.py
tiotools/itio.py
tiotools/tiologparse.py
tiotools/tiomon.py
tldevice/__init__.py
tldevice/tl_cmd_conf.py
tldevice/tl_cmd_data.py
tldevice/tl_cmd_devinfo.py
tldevice/tl_cmds.py
tldevice/tldevice.py
tldevicesync/__init__.py
tldevicesync/tldevicesync.py
tio-3.8.2.dist-info/LICENSE.txt
tio-3.8.2.dist-info/METADATA
tio-3.8.2.dist-info/WHEEL
tio-3.8.2.dist-info/entry_points.txt
tio-3.8.2.dist-info/top_level.txt
tio-3.8.2.dist-info/RECORD
