Metadata-Version: 2.1
Name: tio
Version: 3.8.2
Summary: Helper libraries and utils for Twinleaf I/O (TIO) devices
Home-page: https://github.com/twinleaf/tio-python
Author: Thomas Kornack
Author-email: kornack@twinleaf.com
License: MIT
Requires-Python: >=3.6
License-File: LICENSE.txt
Requires-Dist: PyYAML
Requires-Dist: pyserial
Requires-Dist: hexdump
Requires-Dist: ipython
Requires-Dist: blessings
Requires-Dist: halo
